Metadata-Version: 1.0
Name: futebol-apis
Version: 0.0.3
Summary: Schemas for the FUTEBOL services
Home-page: http://github.com/nerds-ufes/futebol-apis
Author: nerds
Author-email: UNKNOWN
License: MIT
Platform: UNKNOWN
